run.py
jen2jen/__init__.py
jen2jen/jen2jen.py
jen2jen/tiny.py
jen2jen/tools.py
jen2jen-0.2.0.dist-info/METADATA
jen2jen-0.2.0.dist-info/RECORD
jen2jen-0.2.0.dist-info/WHEEL
jen2jen-0.2.0.dist-info/entry_points.txt
jen2jen-0.2.0.dist-info/top_level.txt
